fft_electronic_spin_density/__init__.py
fft_electronic_spin_density/classes.py
fft_electronic_spin_density-0.0.2.dist-info/licenses/LICENSE
fft_electronic_spin_density-0.0.2.dist-info/METADATA
fft_electronic_spin_density-0.0.2.dist-info/WHEEL
fft_electronic_spin_density-0.0.2.dist-info/top_level.txt
fft_electronic_spin_density-0.0.2.dist-info/RECORD
