Metadata-Version: 2.4
Name: fft_electronic_spin_density
Version: 0.0.2
Summary: Perform FFT on Gaussian .cube files of charge or spin density to obtain the (magnetic) form factor for neutron scattering.
Author: L. Vojáček
Author-email: libor.vojacek@psi.ch
License: BSD 3-Clause License
License-File: LICENSE
Requires-Dist: numpy
Requires-Dist: matplotlib
Requires-Dist: scipy
Requires-Dist: pandas
Requires-Dist: pytest
Requires-Dist: pytest-cov
Requires-Dist: pytest-mpl
Dynamic: license-file
